codecaseconverter/__init__.py
codecaseconverter/camelcase_converter.py
codecaseconverter/lowercase_converter.py
codecaseconverter-0.2.dist-info/METADATA
codecaseconverter-0.2.dist-info/WHEEL
codecaseconverter-0.2.dist-info/top_level.txt
codecaseconverter-0.2.dist-info/RECORD
